rsapy/__init__.py
rsapy-0.0.2.data/scripts/rsapy
rsapy-0.0.2.dist-info/METADATA
rsapy-0.0.2.dist-info/WHEEL
rsapy-0.0.2.dist-info/top_level.txt
rsapy-0.0.2.dist-info/RECORD
