Metadata-Version: 2.1
Name: rsapy
Version: 0.0.2
Summary: UNKNOWN
Home-page: https://pypi.org/project/rsapy
Author: Sandra Mattar
Author-email: sandrawmattar1@gmail.com
License: UNKNOWN
Platform: UNKNOWN
